afrimarket/__init__.py
afrimarket/main.py
afrimarket-0.0.1.dist-info/LICENSE.txt
afrimarket-0.0.1.dist-info/METADATA
afrimarket-0.0.1.dist-info/WHEEL
afrimarket-0.0.1.dist-info/top_level.txt
afrimarket-0.0.1.dist-info/RECORD
